setup.py
pypytimer.egg-info/PKG-INFO
pypytimer.egg-info/SOURCES.txt
pypytimer.egg-info/dependency_links.txt
pypytimer.egg-info/not-zip-safe
pypytimer.egg-info/top_level.txt
pythontimer/main.py